{
  "entity": "IMMUNEFI",
  "node": "34539544",
  "compiled_at": "2026-07-19T13:17:59.671753+00:00",
  "digest": "sha256:06ea3a0699324f2391810cc618b5d9025b6b35d76becec91f6a08912fd07f819",
  "own_numbers": {
    "phi_s": 0.02,
    "kappa": 0.0092,
    "mass": 0.038497,
    "power": null,
    "extraction": null,
    "memory_mass": null,
    "X_natural": null,
    "gravity_mass": null,
    "mass_type": null
  },
  "vs_whole": {
    "mass": {
      "value": 0.038497,
      "rank": 150,
      "of": 199
    },
    "power": null,
    "gravity": null,
    "extraction": null,
    "share_of_whole": {
      "mass": 0.00241,
      "power": null
    },
    "peers_by_power": []
  },
  "relationships": {
    "in_degree": 0,
    "out_degree": 1,
    "by_vector": {
      "Capital": {
        "out": 0.0,
        "in": 0.0
      },
      "Infrastructure": {
        "out": 0.0,
        "in": 0.0
      },
      "Information": {
        "out": 0.5,
        "in": 0.0
      }
    },
    "top_inbound": [],
    "top_outbound": [
      {
        "target": "ETHEREUM",
        "conn_type": "information_flow",
        "vector": "Information"
      }
    ],
    "gravity_pairs": []
  },
  "monetary_position": {
    "position": 0.5,
    "well": "fiat"
  },
  "drift": {
    "level": "steady",
    "headline": null,
    "cycles": 65,
    "delta_last_cycle": {
      "phi_s": 0.0,
      "kappa": 0.0,
      "boundary_score": 0.0
    }
  },
  "network_plugs": {
    "freshness": "stale",
    "inbound": [],
    "outbound": [
      {
        "network": "helixhash",
        "status": "live"
      },
      {
        "network": "rfc3161",
        "status": "live"
      },
      {
        "network": "github_pages",
        "status": "live"
      },
      {
        "network": "vercel",
        "status": "live"
      },
      {
        "network": "eas_base",
        "status": "gated"
      }
    ],
    "observation": {
      "source": null,
      "last_observed_at": null,
      "last_delta_i": null,
      "stale": true
    }
  },
  "claims": [
    {
      "claim_id": "9abadbbb-72e4-42a7-bc0d-9f49d3ad3931",
      "claim_text": "Immunefi \u2014 bug bounty platform homepage",
      "grounding": {
        "source_url": "https://immunefi.com/",
        "expected": "Immunefi",
        "location": ""
      },
      "status_at_publish": "ATTESTED-PRIMARY",
      "witness_class": "unknown_secondary",
      "witness_weight": 0.08,
      "report_id": "IMMUNEFI_20260702",
      "report_url": "https://kaydeep0.github.io/eigenstate-research/reports/immunefi-20260702/",
      "verified_at": "2026-07-02T02:55:35.179450+00:00",
      "allows_canonical": true
    },
    {
      "claim_id": "6eeaee55-9546-461e-9d42-bc62d4e79d2d",
      "claim_text": "Immunefi bug bounty programs",
      "grounding": {
        "source_url": "https://immunefi.com/bug-bounty/",
        "expected": "bug bounty",
        "location": ""
      },
      "status_at_publish": "ATTESTED-PRIMARY",
      "witness_class": "unknown_secondary",
      "witness_weight": 0.08,
      "report_id": "IMMUNEFI_20260702",
      "report_url": "https://kaydeep0.github.io/eigenstate-research/reports/immunefi-20260702/",
      "verified_at": "2026-07-02T02:55:35.822663+00:00",
      "allows_canonical": true
    },
    {
      "claim_id": "6e686e49-065e-44a1-a066-1844ae358d3d",
      "claim_text": "Immunefi explore \u2014 active programs",
      "grounding": {
        "source_url": "https://immunefi.com/explore/",
        "expected": "Immunefi",
        "location": ""
      },
      "status_at_publish": "ATTESTED-PRIMARY",
      "witness_class": "unknown_secondary",
      "witness_weight": 0.08,
      "report_id": "IMMUNEFI_20260702",
      "report_url": "https://kaydeep0.github.io/eigenstate-research/reports/immunefi-20260702/",
      "verified_at": "2026-07-02T02:55:36.417817+00:00",
      "allows_canonical": true
    }
  ],
  "claims_mirror": "https://kaydeep0.github.io/eigenstate-research/federation/claims/IMMUNEFI.json"
}