{
  "entity": "PAXOS",
  "node": "34539544",
  "compiled_at": "2026-07-02T16:04:18.861700+00:00",
  "digest": "sha256:8312491f0cf06bac9de0dc2a93866ca75ad525834f6da7ef70eea922b4a11e0f",
  "own_numbers": {
    "phi_s": 3.2362,
    "kappa": 0.3628,
    "mass": null,
    "power": null,
    "extraction": null,
    "memory_mass": null,
    "X_natural": null,
    "gravity_mass": null,
    "mass_type": null
  },
  "vs_whole": {
    "mass": null,
    "power": null,
    "gravity": null,
    "extraction": null,
    "share_of_whole": {
      "mass": null,
      "power": null
    },
    "peers_by_power": []
  },
  "relationships": {
    "in_degree": 0,
    "out_degree": 0,
    "by_vector": {
      "Capital": {
        "out": 0.0,
        "in": 0.0
      },
      "Infrastructure": {
        "out": 0.0,
        "in": 0.0
      },
      "Information": {
        "out": 0.0,
        "in": 0.0
      }
    },
    "top_inbound": [],
    "top_outbound": [],
    "gravity_pairs": []
  },
  "monetary_position": null,
  "drift": {
    "level": "watch",
    "headline": "phi_s -50% over last cycle",
    "cycles": 2,
    "delta_last_cycle": {
      "phi_s": -3.2363,
      "kappa": -0.0009
    }
  },
  "network_plugs": {
    "freshness": "live",
    "inbound": [
      {
        "network": "fred",
        "kind": "macro_primary",
        "status": "live",
        "series_id": "GDP",
        "label": "stablecoin_issuer_gdp_proxy",
        "last_observed_at": "2026-07-02T15:58:53.293670+00:00",
        "note": "fredgraph.csv at feed request time; parkash macro via population_field"
      }
    ],
    "outbound": [
      {
        "network": "helixhash",
        "status": "live"
      },
      {
        "network": "rfc3161",
        "status": "live"
      },
      {
        "network": "github_pages",
        "status": "live"
      },
      {
        "network": "vercel",
        "status": "live"
      },
      {
        "network": "eas_base",
        "status": "gated"
      }
    ],
    "observation": null
  },
  "relative_to_node": {
    "node_field_G_345": 98022413.7478714,
    "is_current_operator_target": false,
    "is_next_optimal_move": false,
    "minus_one_bias": null,
    "operator_move": null,
    "observed_by_node": false
  }
}