{
  "entity": "STANI_KULECHOV",
  "node": "34539544",
  "compiled_at": "2026-07-18T03:06:08.238314+00:00",
  "digest": "sha256:3055926838ceb1f740c7f026c5e5d165ac6af48c7267f9c61df215e5d9078179",
  "own_numbers": {
    "phi_s": 0.02,
    "kappa": 0.0459,
    "mass": 0.102568,
    "power": 0.0,
    "extraction": 1180.4681,
    "memory_mass": null,
    "X_natural": null,
    "gravity_mass": null,
    "mass_type": null
  },
  "vs_whole": {
    "mass": {
      "value": 0.102568,
      "rank": 37,
      "of": 199
    },
    "power": {
      "value": 0.0,
      "rank": 45,
      "of": 51
    },
    "gravity": null,
    "extraction": {
      "value": 1180.4681,
      "rank": 33,
      "of": 51
    },
    "share_of_whole": {
      "mass": 0.00641,
      "power": 0.0
    },
    "peers_by_power": [
      {
        "entity": "SECURITIZE",
        "power": 0.0
      },
      {
        "entity": "STABLECOIN_POOL",
        "power": 0.0
      },
      {
        "entity": "STANI_KULECHOV",
        "power": 0.0
      },
      {
        "entity": "STRONGHOLD",
        "power": 0.0
      },
      {
        "entity": "TETHER",
        "power": 0.0
      }
    ]
  },
  "relationships": {
    "in_degree": 0,
    "out_degree": 5,
    "by_vector": {
      "Capital": {
        "out": 0.0,
        "in": 0.0
      },
      "Infrastructure": {
        "out": 1.0,
        "in": 0.0
      },
      "Information": {
        "out": 1.5,
        "in": 0.0
      }
    },
    "top_inbound": [],
    "top_outbound": [
      {
        "target": "AAVE_GOVERNANCE",
        "conn_type": "governance",
        "vector": "Infrastructure"
      },
      {
        "target": "ROBERT_LESHNER",
        "conn_type": "information_flow",
        "vector": "Information"
      },
      {
        "target": "LENS_PROTOCOL",
        "conn_type": "information_flow",
        "vector": "Information"
      },
      {
        "target": "FARCASTER",
        "conn_type": "information_flow",
        "vector": "Information"
      },
      {
        "target": "AAVE_GOVERNANCE",
        "conn_type": "governance",
        "vector": "Infrastructure"
      }
    ],
    "gravity_pairs": []
  },
  "monetary_position": {
    "position": 0.5,
    "well": "fiat"
  },
  "drift": {
    "level": "steady",
    "headline": null,
    "cycles": 56,
    "delta_last_cycle": {
      "phi_s": 0.0,
      "kappa": 0.0,
      "power": 0.0,
      "extraction": 73.2294,
      "boundary_score": 0.0
    }
  },
  "network_plugs": {
    "freshness": "stale",
    "inbound": [],
    "outbound": [
      {
        "network": "helixhash",
        "status": "live"
      },
      {
        "network": "rfc3161",
        "status": "live"
      },
      {
        "network": "github_pages",
        "status": "live"
      },
      {
        "network": "vercel",
        "status": "live"
      },
      {
        "network": "eas_base",
        "status": "gated"
      }
    ],
    "observation": {
      "source": null,
      "last_observed_at": "2026-07-01T22:28:54.946884+00:00",
      "last_delta_i": null,
      "stale": true
    }
  },
  "claims": [
    {
      "claim_id": "dbe9951f-efb6-4b0f-8405-e8c60515285c",
      "claim_text": "Stani Kulechov \u2014 Aave about page",
      "grounding": {
        "source_url": "https://aave.com/about",
        "expected": "Stani",
        "location": ""
      },
      "status_at_publish": "ATTESTED-PRIMARY",
      "witness_class": "unknown_secondary",
      "witness_weight": 0.08,
      "report_id": "STANI_KULECHOV_20260702",
      "report_url": "https://kaydeep0.github.io/eigenstate-research/reports/stani-kulechov-20260702/",
      "verified_at": "2026-07-02T03:43:42.165309+00:00",
      "allows_canonical": true
    },
    {
      "claim_id": "f762cebf-4b70-431e-a233-68171d9bac71",
      "claim_text": "Aave governance forum",
      "grounding": {
        "source_url": "https://governance.aave.com/",
        "expected": "governance",
        "location": ""
      },
      "status_at_publish": "ATTESTED-PRIMARY",
      "witness_class": "unknown_secondary",
      "witness_weight": 0.08,
      "report_id": "STANI_KULECHOV_20260702",
      "report_url": "https://kaydeep0.github.io/eigenstate-research/reports/stani-kulechov-20260702/",
      "verified_at": "2026-07-02T03:43:42.930034+00:00",
      "allows_canonical": true
    },
    {
      "claim_id": "0d527e5f-5571-4f17-93cb-d5d3c6dac126",
      "claim_text": "Aave protocol documentation",
      "grounding": {
        "source_url": "https://docs.aave.com/faq/aave-basics",
        "expected": "Aave",
        "location": ""
      },
      "status_at_publish": "ATTESTED-PRIMARY",
      "witness_class": "unknown_secondary",
      "witness_weight": 0.08,
      "report_id": "STANI_KULECHOV_20260702",
      "report_url": "https://kaydeep0.github.io/eigenstate-research/reports/stani-kulechov-20260702/",
      "verified_at": "2026-07-02T03:43:43.133520+00:00",
      "allows_canonical": true
    }
  ],
  "claims_mirror": "https://kaydeep0.github.io/eigenstate-research/federation/claims/STANI_KULECHOV.json"
}