{
  "entity": "CIRCLE_USYC",
  "node": "34539544",
  "compiled_at": "2026-07-21T04:51:55.867045+00:00",
  "digest": "sha256:4a9cd33cbb445d1fec1d2a71ad787720774ebd5c1e91532ac031c4d066a208ca",
  "own_numbers": {
    "phi_s": 0.02,
    "kappa": 0.0145,
    "mass": 0.038497,
    "power": null,
    "extraction": null,
    "memory_mass": null,
    "X_natural": null,
    "gravity_mass": null,
    "mass_type": null
  },
  "vs_whole": {
    "mass": {
      "value": 0.038497,
      "rank": 154,
      "of": 199
    },
    "power": null,
    "gravity": null,
    "extraction": null,
    "share_of_whole": {
      "mass": 0.00239,
      "power": null
    },
    "peers_by_power": []
  },
  "relationships": {
    "in_degree": 1,
    "out_degree": 1,
    "by_vector": {
      "Capital": {
        "out": 0.0,
        "in": 0.0
      },
      "Infrastructure": {
        "out": 0.0,
        "in": 0.0
      },
      "Information": {
        "out": 0.5,
        "in": 0.0103
      }
    },
    "top_inbound": [
      {
        "source": "34539544",
        "conn_type": "strategic",
        "vector": "Information"
      }
    ],
    "top_outbound": [
      {
        "target": "ETHEREUM",
        "conn_type": "information_flow",
        "vector": "Information"
      }
    ],
    "gravity_pairs": []
  },
  "monetary_position": {
    "position": 0.5,
    "well": "fiat"
  },
  "drift": {
    "level": "steady",
    "headline": null,
    "cycles": 74,
    "delta_last_cycle": {
      "phi_s": 0.0,
      "kappa": 0.0,
      "boundary_score": 0.0
    }
  },
  "network_plugs": {
    "freshness": "stale",
    "inbound": [],
    "outbound": [
      {
        "network": "helixhash",
        "status": "live"
      },
      {
        "network": "rfc3161",
        "status": "live"
      },
      {
        "network": "github_pages",
        "status": "live"
      },
      {
        "network": "vercel",
        "status": "live"
      },
      {
        "network": "eas_base",
        "status": "gated"
      }
    ],
    "observation": {
      "source": null,
      "last_observed_at": null,
      "last_delta_i": null,
      "stale": true
    }
  },
  "claims": [
    {
      "claim_id": "6f39fd89-f489-4d52-901f-bec1b557f3cf",
      "claim_text": "Circle USYC \u2014 tokenized money market fund overview",
      "grounding": {
        "source_url": "https://developers.circle.com/tokenized/usyc/overview",
        "expected": "USYC",
        "location": ""
      },
      "status_at_publish": "ATTESTED-PRIMARY",
      "witness_class": "unknown_secondary",
      "witness_weight": 0.08,
      "report_id": "CIRCLE_USYC_20260702",
      "report_url": "https://kaydeep0.github.io/eigenstate-research/reports/circle-usyc-20260702/",
      "verified_at": "2026-07-02T17:25:47.105426+00:00",
      "allows_canonical": true
    },
    {
      "claim_id": "e287c324-fbe3-45ec-b67e-0b5157dfcc58",
      "claim_text": "USYC issued by Circle International Bermuda",
      "grounding": {
        "source_url": "https://developers.circle.com/tokenized/usyc/overview",
        "expected": "Circle",
        "location": ""
      },
      "status_at_publish": "ATTESTED-PRIMARY",
      "witness_class": "unknown_secondary",
      "witness_weight": 0.08,
      "report_id": "CIRCLE_USYC_20260702",
      "report_url": "https://kaydeep0.github.io/eigenstate-research/reports/circle-usyc-20260702/",
      "verified_at": "2026-07-02T17:25:47.230210+00:00",
      "allows_canonical": true
    },
    {
      "claim_id": "8bde0d4c-5b31-4d20-aeb4-6b1594f54728",
      "claim_text": "USYC onchain settlement via USDC",
      "grounding": {
        "source_url": "https://developers.circle.com/tokenized/usyc/overview",
        "expected": "onchain",
        "location": ""
      },
      "status_at_publish": "ATTESTED-PRIMARY",
      "witness_class": "unknown_secondary",
      "witness_weight": 0.08,
      "report_id": "CIRCLE_USYC_20260702",
      "report_url": "https://kaydeep0.github.io/eigenstate-research/reports/circle-usyc-20260702/",
      "verified_at": "2026-07-02T17:25:47.361753+00:00",
      "allows_canonical": true
    }
  ],
  "claims_mirror": "https://kaydeep0.github.io/eigenstate-research/federation/claims/CIRCLE_USYC.json"
}